superimposer/__init__.py
superimposer-0.1.3.dist-info/WHEEL
superimposer-0.1.3.dist-info/entry_points.txt
superimposer-0.1.3.dist-info/METADATA
superimposer-0.1.3.dist-info/RECORD
