Metadata-Version: 2.4
Name: superimposer
Version: 0.1.3
Summary: Superimpose presentation records onto PDF slides
Keywords: presentation,slides,video,ffmpeg
Author: Jon Gjengset
Author-email: Jon Gjengset <jon@thesquareplanet.com>
License-Expression: MIT
Classifier: Development Status :: 4 - Beta
Classifier: Intended Audience :: Developers
Classifier: Intended Audience :: End Users/Desktop
Classifier: Topic :: Multimedia :: Graphics :: Presentation
Classifier: Topic :: Multimedia :: Video
Classifier: Natural Language :: English
Classifier: License :: OSI Approved :: MIT License
Classifier: Environment :: Console
Classifier: Operating System :: POSIX
Classifier: Programming Language :: Python :: 3
Requires-Dist: pypdf>=6.0.0
Maintainer: Jon Gjengset
Maintainer-email: Jon Gjengset <jon@thesquareplanet.com>
Requires-Python: >=3.9
Project-URL: funding, https://github.com/sponsors/jonhoo/
Project-URL: homepage, https://github.com/jonhoo/superimposer
Project-URL: issues, https://github.com/jonhoo/superimposer/issues
